pyspec/__init__.py
pyspec/_connection/__init__.py
pyspec/_connection/associative_array.py
pyspec/_connection/client_connection.py
pyspec/_connection/command.py
pyspec/_connection/connection.py
pyspec/_connection/data.py
pyspec/_connection/flag.py
pyspec/_connection/protocol.py
pyspec/_connection/server_connection.py
pyspec/client/__init__.py
pyspec/client/_motor.py
pyspec/client/_remote_property_table.py
pyspec/client/_status.py
pyspec/client/client.py
pyspec/file/__init__.py
pyspec/file/css_logger.py
pyspec/file/h5datasets.py
pyspec/file/hamamatsu.py
pyspec/file/hdf5.py
pyspec/file/spec.py
pyspec/server/__init__.py
pyspec/server/_remote_function.py
pyspec/server/_remote_property.py
pyspec/server/server.py
pyspec/shared_memory/datashm_py.c
pyspec/shared_memory/shared_memory.cpython-39-aarch64-linux-gnu.so
pyspec/shared_memory/spec_shm.h
pyspec/shared_memory/sps.c
pyspec/shared_memory/sps.h
chess_pyspec-1.0.1.dist-info/METADATA
chess_pyspec-1.0.1.dist-info/WHEEL
chess_pyspec-1.0.1.dist-info/top_level.txt
chess_pyspec-1.0.1.dist-info/RECORD
chess_pyspec-1.0.1.dist-info/licenses/LICENSE
