Metadata-Version: 2.4
Name: chess-pyspec
Version: 1.0.1
Summary: Python SPEC modules and tools
Author-email: Kevin Welsh <kevin.welsh@verdantevolution.com>
Project-URL: Homepage, https://github.com/Verdant-Evolution/chess-pyspec
Requires-Python: >=3.9
License-File: LICENSE
Requires-Dist: cython>=3.2.3
Requires-Dist: h5py>=3.0.0
Requires-Dist: numpy
Requires-Dist: pyee>=13.0.0
Provides-Extra: dev
Requires-Dist: sphinx; extra == "dev"
Requires-Dist: sphinx-autodoc-typehints; extra == "dev"
Requires-Dist: sphinx-rtd-theme; extra == "dev"
Requires-Dist: python-docs-theme; extra == "dev"
Provides-Extra: test
Requires-Dist: pytest-asyncio; extra == "test"
Requires-Dist: pytest-cov; extra == "test"
Requires-Dist: pytest-timeout; extra == "test"
Dynamic: license-file
